{"id":"AbCdEfGhIjKlMnOpQrStUv","title":"Federated fixture live session","webpage_url":"https://peertube.example.test/videos/watch/AbCdEfGhIjKlMnOpQrStUv","ext":"mp4","is_live":true,"description":"Complete deterministic PeerTube fixture description returned by the optional description endpoint.","thumbnail":"https://peertube.example.test/lazy-static/thumbnails/fixture.jpg","timestamp":1752842096,"duration":3723,"view_count":1234,"like_count":45,"dislike_count":2,"uploader":"Fixture Uploader","uploader_id":"7","uploader_url":"https://peertube.example.test/accounts/fixture-account","channel":"Fixture Channel","channel_id":"9","channel_url":"https://peertube.example.test/video-channels/fixture-channel","language":"en","license":"Attribution","age_limit":0,"live_status":"is_live","categories":["Education"],"tags":["federation","fixture"],"format_ids":["0p","1080p","720p","hls-1"],"subtitle_languages":["en","fr"]}
